dash_pydantic_utils/__init__.py
dash_pydantic_utils/common.py
dash_pydantic_utils/path.py
dash_pydantic_utils/types.py
dash_pydantic_utils/quantity/__init__.py
dash_pydantic_utils/quantity/pandas_engine.py
dash_pydantic_utils/quantity/quantity.py
dash_pydantic_utils-0.18.3.dist-info/METADATA
dash_pydantic_utils-0.18.3.dist-info/WHEEL
dash_pydantic_utils-0.18.3.dist-info/licenses/LICENSE
dash_pydantic_utils-0.18.3.dist-info/RECORD
