Metadata-Version: 2.4
Name: dash-pydantic-utils
Version: 0.18.3
Summary: Utils for dash-pydantic-form, allows to use the utils in other places without requiring Dash.
Project-URL: Source, https://github.com/RenaudLN/dash-pydantic-form
Author-email: Renaud Lainé <renaudlaine31@gmail.com>
License: The MIT License (MIT)
License-File: LICENSE
Requires-Python: <3.14,>=3.10
Requires-Dist: pydantic==2.*
Provides-Extra: dev
Requires-Dist: pre-commit; extra == 'dev'
Requires-Dist: pytest; extra == 'dev'
Provides-Extra: pandas
Requires-Dist: numpy; extra == 'pandas'
Requires-Dist: pandas; extra == 'pandas'
